wxee/__init__.py
wxee/accessors.py
wxee/climatology.py
wxee/collection.py
wxee/constants.py
wxee/exceptions.py
wxee/image.py
wxee/interpolation.py
wxee/params.py
wxee/time_series.py
wxee/utils.py
wxee/xarray.py
wxee-0.5.0.dist-info/METADATA
wxee-0.5.0.dist-info/WHEEL
wxee-0.5.0.dist-info/licenses/LICENSE
wxee-0.5.0.dist-info/RECORD
