Metadata-Version: 2.4
Name: wxee
Version: 0.5.0
Summary: Earth Engine to xarray interface
Project-URL: Homepage, https://github.com/aazuspan/wxee
Author-email: Aaron Zuspan <aazuspan@gmail.com>
License-Expression: MIT
License-File: LICENSE
Keywords: earth-engine,time-series,xarray
Classifier: Development Status :: 4 - Beta
Classifier: Intended Audience :: Science/Research
Classifier: Natural Language :: English
Classifier: Programming Language :: Python :: 3
Classifier: Programming Language :: Python :: 3.8
Classifier: Programming Language :: Python :: 3.9
Classifier: Programming Language :: Python :: 3.10
Classifier: Programming Language :: Python :: 3.11
Classifier: Programming Language :: Python :: 3.12
Classifier: Programming Language :: Python :: 3.13
Classifier: Topic :: Scientific/Engineering :: GIS
Classifier: Typing :: Typed
Requires-Python: >=3.8
Requires-Dist: earthengine-api
Requires-Dist: joblib
Requires-Dist: rasterio
Requires-Dist: requests
Requires-Dist: rioxarray
Requires-Dist: tqdm
Requires-Dist: xarray
